buslytics/__init__.py
buslytics/main.py
buslytics/prompts.py
buslytics-2025.12.21154840.dist-info/METADATA
buslytics-2025.12.21154840.dist-info/WHEEL
buslytics-2025.12.21154840.dist-info/top_level.txt
buslytics-2025.12.21154840.dist-info/RECORD
