Metadata-Version: 2.4
Name: buslytics
Version: 2025.12.21154840
Summary: A new package that processes text input to monitor and analyze the health and performance of a message bus system. It uses natural language queries to return structured insights about message throughp
Author-email: buslytics <hi@eugene.plus>
License: MIT
Project-URL: Homepage, https://github.com/chigwell/buslytics
Requires-Python: >=3.9
Requires-Dist: langchain-llm7>=0.0.0
Requires-Dist: llmatch-messages>=0.0.0
Requires-Dist: langchain-core>=0.3.0
